elinkapi/__init__.py
elinkapi/__version__.py
elinkapi/affiliation.py
elinkapi/auditlogs.py
elinkapi/contribution.py
elinkapi/elinkapi.py
elinkapi/exceptions.py
elinkapi/geolocation.py
elinkapi/identifier.py
elinkapi/media_file.py
elinkapi/media_info.py
elinkapi/organization.py
elinkapi/person.py
elinkapi/query.py
elinkapi/record.py
elinkapi/related_identifier.py
elinkapi/revision.py
elinkapi/revision_comparison.py
elinkapi/utils.py
elinkapi-0.5.3.dist-info/licenses/LICENSE
elinkapi-0.5.3.dist-info/METADATA
elinkapi-0.5.3.dist-info/WHEEL
elinkapi-0.5.3.dist-info/top_level.txt
elinkapi-0.5.3.dist-info/RECORD
