Metadata-Version: 2.4
Name: elinkapi
Version: 0.5.3
Summary: OSTI E-Link 2 API package
Author: Jacob Samar
Author-email: Neal Ensor <ensorn@osti.gov>
Project-URL: Homepage, https://github.com/doecode/elinkapi
Project-URL: Issues, https://github.com/doecode/elinkapi/issues
Project-URL: Changelog, https://github.com/doecode/elinkapi/blob/main/CHANGELOG.md
Project-URL: Examples, https://github.com/doecode/elinkapi/tree/main/examples
Classifier: Programming Language :: Python :: 3
Classifier: License :: OSI Approved :: BSD License
Classifier: Operating System :: OS Independent
Requires-Python: >=3.9
License-File: LICENSE
Requires-Dist: requests
Requires-Dist: pydantic
Requires-Dist: urllib3
Requires-Dist: requests_toolbelt
Provides-Extra: development
Requires-Dist: twine; extra == "development"
Requires-Dist: build; extra == "development"
Dynamic: license-file
